Mensaje/__init__.py
Mensaje/adios/__init__.py
Mensaje/adios/despedidas.py
Mensaje/hola/__init__.py
Mensaje/hola/saludos.py
tests/__init__.py
tests/test_hola.py
Mensaje_CEGM-7.0.dist-info/LICENSE
Mensaje_CEGM-7.0.dist-info/METADATA
Mensaje_CEGM-7.0.dist-info/WHEEL
Mensaje_CEGM-7.0.dist-info/top_level.txt
Mensaje_CEGM-7.0.dist-info/RECORD
