Metadata-Version: 2.1
Name: Mensaje-CEGM
Version: 7.0
Summary: Un paquete de saludos y despedidas.
Home-page: 
Author: Carolina Gómez Muñoz
Author-email: cgomez33@ucol.mx
Classifier: Environment :: Console
Classifier: Intended Audience :: Developers
Classifier: License :: OSI Approved :: MIT License
Classifier: Operating System :: OS Independent
Classifier: Programming Language :: Python
Classifier: Programming Language :: Python :: 3
Classifier: Topic :: Software Development :: Libraries :: Python Modules
License-File: LICENSE
Requires-Dist: numpy >=2.1.0
